{
	"sidebar": [
		"app.modules",
		"app.roles",
		"moduleTemplate"
	],
	"common": {
		"main": "common.js",
		"dependencies":[
			"services/server-api.js",
			"services/auth.js",
			"services/localization.js"
		]
	},
	"vendorModules":{

	},
	"coreModules": {
		"app.datatable": {
			"main":	"datatable/datatable.js"
		},
		"app.sidebar": {
			"main":	"sidebar/sidebar.js",
			"dependencies": [
				"sidebar/services/sidebar-service.js"
			]
		},
		"app.modules": {
			"info": {
				"name": "Modules",
				"url": "/modules"
			},
			"main": "modules/modules.js",
			"dependencies": [
				"modules/controllers/modules-controller.js"
			]
		},
		"app.roles": {
			"info": {
				"name": "Roles",
				"url": "/roles"
			},
			"main": "roles/roles.js",
			"dependencies": [
				"roles/controllers/roles-controller.js"
			]
		}
	},
	"userModules": {
		"moduleTemplate": {
			"info": {
				"name": "Module template",
				"url": "/module_template"
			},
			"main": "module_template/module-template.js",
			"dependencies": [
				"module_template/controllers/module-template-controller.js"
			]
		}
	}
}